wagtail_favicon/__init__.py
wagtail_favicon/apps.py
wagtail_favicon/migrations/0001_initial.py
wagtail_favicon/migrations/0002_remove_social_sharing_image_setting.py
wagtail_favicon/migrations/__init__.py
wagtail_favicon/models.py
wagtail_favicon/templates/browser-config.xml
wagtail_favicon/templates/tags/favicon_meta.html
wagtail_favicon/templatetags/favicon_tags.py
wagtail_favicon/urls.py
wagtail_favicon/validators.py
wagtail_favicon/views.py
wagtail_favicon-0.3.0.dist-info/METADATA
wagtail_favicon-0.3.0.dist-info/WHEEL
wagtail_favicon-0.3.0.dist-info/RECORD
