Metadata-Version: 2.1
Name: wagtail-favicon
Version: 0.3.0
Summary: Easily add shortcut icons to any wagtail site.
Home-page: https://github.com/octavenz/wagtail-favicon
License: BSD
Author: Pat Horsley
Author-email: support@octave.nz
Classifier: License :: Other/Proprietary License
Classifier: Programming Language :: Python :: 2
Classifier: Programming Language :: Python :: 2.7
Classifier: Programming Language :: Python :: 3
Classifier: Programming Language :: Python :: 3.4
Classifier: Programming Language :: Python :: 3.5
Classifier: Programming Language :: Python :: 3.6
Classifier: Programming Language :: Python :: 3.7
Classifier: Programming Language :: Python :: 3.8
Classifier: Programming Language :: Python :: 3.9
Classifier: Programming Language :: Python :: 3.10
Classifier: Programming Language :: Python :: 3.11
